BuckTheDuck/__init__.py
BuckTheDuck/__main__.py
BuckTheDuck/common/__init__.py
BuckTheDuck/common/file_path_utilities.py
BuckTheDuck/common/singleton.py
BuckTheDuck/common/exceptions/__init__.py
BuckTheDuck/common/generative_ai/__init__.py
BuckTheDuck/common/generative_ai/base_generative_ai.py
BuckTheDuck/common/generative_ai/config.py
BuckTheDuck/common/generative_ai/gemini_accessor.py
BuckTheDuck/common/generative_ai/gen_ai_type.py
BuckTheDuck/common/generative_ai/generative_ai_factory.py
BuckTheDuck/common/generative_ai/generative_ai_strategy.py
BuckTheDuck/common/generative_ai/openai_accessor.py
BuckTheDuck/common/git/__init__.py
BuckTheDuck/common/git/file_filter.py
BuckTheDuck/common/git/git_providers/__init__.py
BuckTheDuck/common/git/git_providers/git_accessor.py
BuckTheDuck/common/git/git_providers/parsers/__init__.py
BuckTheDuck/common/git/git_providers/parsers/git_log.py
BuckTheDuck/common/types/__init__.py
BuckTheDuck/common/types/commit_changes.py
BuckTheDuck/common/types/git_diff_level.py
BuckTheDuck/common/types/moved_file.py
BuckTheDuck/documentor/__init__.py
BuckTheDuck/documentor/documentation_manager.py
BuckTheDuck/documentor/file_mapping.py
BuckTheDuck/documentor/file_documentor/__init__.py
BuckTheDuck/documentor/file_documentor/file_documentor.py
BuckTheDuck/documentor/file_documentor/language_parser/__init__.py
BuckTheDuck/documentor/file_documentor/language_parser/base_language_parser.py
BuckTheDuck/documentor/file_documentor/language_parser/python_parser.py
BuckTheDuck/extractors/__init__.py
BuckTheDuck/extractors/base_extractor.py
BuckTheDuck/extractors/extractor_factory.py
BuckTheDuck/extractors/nodejs_extractor.py
BuckTheDuck/extractors/python_code_extractor.py
BuckTheDuck/extractors/ast_parser/__init__.py
BuckTheDuck/extractors/ast_parser/nodejs_ast.py
BuckTheDuck/extractors/ast_parser/nodejs_ast_parser.py
BuckTheDuck/extractors/types/__init__.py
BuckTheDuck/extractors/types/extracted_commit_changes.py
BuckTheDuck-0.0.4.dist-info/METADATA
BuckTheDuck-0.0.4.dist-info/WHEEL
BuckTheDuck-0.0.4.dist-info/entry_points.txt
BuckTheDuck-0.0.4.dist-info/top_level.txt
BuckTheDuck-0.0.4.dist-info/RECORD
